odoo10_addon_stock_inventory_barcode-10.0.0.1.0.99.dev4-py3.8-nspkg.pth
odoo/addons/stock_inventory_barcode/README.rst
odoo/addons/stock_inventory_barcode/__init__.py
odoo/addons/stock_inventory_barcode/__manifest__.py
odoo/addons/stock_inventory_barcode/i18n/am.po
odoo/addons/stock_inventory_barcode/i18n/ar.po
odoo/addons/stock_inventory_barcode/i18n/bg.po
odoo/addons/stock_inventory_barcode/i18n/bs.po
odoo/addons/stock_inventory_barcode/i18n/ca.po
odoo/addons/stock_inventory_barcode/i18n/ca_ES.po
odoo/addons/stock_inventory_barcode/i18n/cs.po
odoo/addons/stock_inventory_barcode/i18n/da.po
odoo/addons/stock_inventory_barcode/i18n/de.po
odoo/addons/stock_inventory_barcode/i18n/el_GR.po
odoo/addons/stock_inventory_barcode/i18n/en_AU.po
odoo/addons/stock_inventory_barcode/i18n/en_GB.po
odoo/addons/stock_inventory_barcode/i18n/es.po
odoo/addons/stock_inventory_barcode/i18n/es_AR.po
odoo/addons/stock_inventory_barcode/i18n/es_CL.po
odoo/addons/stock_inventory_barcode/i18n/es_CO.po
odoo/addons/stock_inventory_barcode/i18n/es_CR.po
odoo/addons/stock_inventory_barcode/i18n/es_DO.po
odoo/addons/stock_inventory_barcode/i18n/es_EC.po
odoo/addons/stock_inventory_barcode/i18n/es_ES.po
odoo/addons/stock_inventory_barcode/i18n/es_MX.po
odoo/addons/stock_inventory_barcode/i18n/es_PE.po
odoo/addons/stock_inventory_barcode/i18n/es_PY.po
odoo/addons/stock_inventory_barcode/i18n/es_VE.po
odoo/addons/stock_inventory_barcode/i18n/et.po
odoo/addons/stock_inventory_barcode/i18n/eu.po
odoo/addons/stock_inventory_barcode/i18n/fa.po
odoo/addons/stock_inventory_barcode/i18n/fi.po
odoo/addons/stock_inventory_barcode/i18n/fr.po
odoo/addons/stock_inventory_barcode/i18n/fr_CH.po
odoo/addons/stock_inventory_barcode/i18n/fr_FR.po
odoo/addons/stock_inventory_barcode/i18n/gl.po
odoo/addons/stock_inventory_barcode/i18n/gl_ES.po
odoo/addons/stock_inventory_barcode/i18n/he.po
odoo/addons/stock_inventory_barcode/i18n/hi.po
odoo/addons/stock_inventory_barcode/i18n/hr.po
odoo10_addon_stock_inventory_barcode-10.0.0.1.0.99.dev4.dist-info/METADATA
odoo10_addon_stock_inventory_barcode-10.0.0.1.0.99.dev4.dist-info/WHEEL
odoo10_addon_stock_inventory_barcode-10.0.0.1.0.99.dev4.dist-info/namespace_packages.txt
odoo10_addon_stock_inventory_barcode-10.0.0.1.0.99.dev4.dist-info/top_level.txt
odoo10_addon_stock_inventory_barcode-10.0.0.1.0.99.dev4.dist-info/RECORD
