Metadata-Version: 2.1
Name: odoo10-addon-stock-inventory-barcode
Version: 10.0.0.1.0.99.dev4
Summary: Add simple barcode interface on inventories
Home-page: UNKNOWN
Author: Akretion,Odoo Community Association (OCA)
Author-email: support@odoo-community.org
License: AGPL-3
Platform: UNKNOWN
Classifier: Programming Language :: Python
Classifier: Framework :: Odoo
Classifier: Framework :: Odoo :: 10.0
Classifier: License :: OSI Approved :: GNU Affero General Public License v3
Requires-Python: ~=2.7
Requires-Dist: odoo (<10.1dev,>=10.0)
